{
  "result": {
    "dataset": "photo",
    "variant": "dual_static",
    "seed": 1,
    "epochs": 120,
    "best_epoch": 118,
    "best_val_acc": 0.7045751810073853,
    "best_test_acc": 0.7184640765190125,
    "final_train_acc": 0.7320261597633362,
    "final_val_acc": 0.6993464231491089,
    "final_test_acc": 0.715032696723938,
    "graph_keep": 0.6999999284744263,
    "graph_sparsity": 0.30000007152557373,
    "param_keep": 0.7000000476837158,
    "param_sparsity": 0.2999999523162842,
    "graph_churn": 0.0028571465518325567,
    "param_churn": 0.0028858445584774017,
    "graph_memory_state_norm": 0.0,
    "param_memory_state_norm": 0.0,
    "runtime_sec": 2.1116316318511963,
    "num_nodes": 7650,
    "num_edges": 238162,
    "hidden_dim": 64,
    "memory_rank": 16
  },
  "history": [
    {
      "epoch": 0,
      "loss": 2.0794718265533447,
      "task_loss": 2.0794718265533447,
      "train_acc": 0.26143792271614075,
      "val_acc": 0.24705882370471954,
      "test_acc": 0.2535947859287262,
      "best_val": 0.24705882370471954,
      "best_test": 0.2535947859287262,
      "temperature": 2.0,
      "graph_keep": 1.0,
      "param_keep": 1.0,
      "graph_churn": 0.0,
      "param_churn": 0.0
    },
    {
      "epoch": 1,
      "loss": 2.077125310897827,
      "task_loss": 2.077125310897827,
      "train_acc": 0.26143792271614075,
      "val_acc": 0.24705882370471954,
      "test_acc": 0.2535947859287262,
      "best_val": 0.24705882370471954,
      "best_test": 0.2535947859287262,
      "temperature": 1.976836121252429,
      "graph_keep": 1.0,
      "param_keep": 1.0,
      "graph_churn": 0.0,
      "param_churn": 0.0
    },
    {
      "epoch": 2,
      "loss": 2.073894739151001,
      "task_loss": 2.073894739151001,
      "train_acc": 0.26143792271614075,
      "val_acc": 0.24705882370471954,
      "test_acc": 0.2535947859287262,
      "best_val": 0.24705882370471954,
      "best_test": 0.2535947859287262,
      "temperature": 1.9539405251441744,
      "graph_keep": 1.0,
      "param_keep": 1.0,
      "graph_churn": 0.0,
      "param_churn": 0.0
    },
    {
      "epoch": 3,
      "loss": 2.06968092918396,
      "task_loss": 2.06968092918396,
      "train_acc": 0.26143792271614075,
      "val_acc": 0.24705882370471954,
      "test_acc": 0.2535947859287262,
      "best_val": 0.24705882370471954,
      "best_test": 0.2535947859287262,
      "temperature": 1.931310104441972,
      "graph_keep": 1.0,
      "param_keep": 1.0,
      "graph_churn": 0.0,
      "param_churn": 0.0
    },
    {
      "epoch": 4,
      "loss": 2.0638463497161865,
      "task_loss": 2.0638463497161865,
      "train_acc": 0.26143792271614075,
      "val_acc": 0.24705882370471954,
      "test_acc": 0.2535947859287262,
      "best_val": 0.24705882370471954,
      "best_test": 0.2535947859287262,
      "temperature": 1.9089417879003459,
      "graph_keep": 1.0,
      "param_keep": 1.0,
      "graph_churn": 0.0,
      "param_churn": 0.0
    },
    {
      "epoch": 5,
      "loss": 2.056480646133423,
      "task_loss": 2.056480646133423,
      "train_acc": 0.26143792271614075,
      "val_acc": 0.24705882370471954,
      "test_acc": 0.2535947859287262,
      "best_val": 0.24705882370471954,
      "best_test": 0.2535947859287262,
      "temperature": 1.8868325398447985,
      "graph_keep": 1.0,
      "param_keep": 1.0,
      "graph_churn": 0.0,
      "param_churn": 0.0
    },
    {
      "epoch": 6,
      "loss": 2.04876708984375,
      "task_loss": 2.04876708984375,
      "train_acc": 0.26143792271614075,
      "val_acc": 0.24705882370471954,
      "test_acc": 0.2535947859287262,
      "best_val": 0.24705882370471954,
      "best_test": 0.2535947859287262,
      "temperature": 1.8649793597598303,
      "graph_keep": 1.0,
      "param_keep": 1.0,
      "graph_churn": 0.0,
      "param_churn": 0.0
    },
    {
      "epoch": 7,
      "loss": 2.0378730297088623,
      "task_loss": 2.0378730297088623,
      "train_acc": 0.26143792271614075,
      "val_acc": 0.24705882370471954,
      "test_acc": 0.2535947859287262,
      "best_val": 0.24705882370471954,
      "best_test": 0.2535947859287262,
      "temperature": 1.8433792818817307,
      "graph_keep": 1.0,
      "param_keep": 1.0,
      "graph_churn": 0.0,
      "param_churn": 0.0
    },
    {
      "epoch": 8,
      "loss": 2.026991367340088,
      "task_loss": 2.026991367340088,
      "train_acc": 0.26143792271614075,
      "val_acc": 0.24705882370471954,
      "test_acc": 0.2535947859287262,
      "best_val": 0.24705882370471954,
      "best_test": 0.2535947859287262,
      "temperature": 1.8220293747960845,
      "graph_keep": 1.0,
      "param_keep": 1.0,
      "graph_churn": 0.0,
      "param_churn": 0.0
    },
    {
      "epoch": 9,
      "loss": 2.016878366470337,
      "task_loss": 2.016878366470337,
      "train_acc": 0.26143792271614075,
      "val_acc": 0.24705882370471954,
      "test_acc": 0.2535947859287262,
      "best_val": 0.24705882370471954,
      "best_test": 0.2535947859287262,
      "temperature": 1.80092674103994,
      "graph_keep": 1.0,
      "param_keep": 1.0,
      "graph_churn": 0.0,
      "param_churn": 0.0
    },
    {
      "epoch": 10,
      "loss": 2.0054001808166504,
      "task_loss": 2.0054001808166504,
      "train_acc": 0.26143792271614075,
      "val_acc": 0.24705882370471954,
      "test_acc": 0.2535947859287262,
      "best_val": 0.24705882370471954,
      "best_test": 0.2535947859287262,
      "temperature": 1.7800685167085863,
      "graph_keep": 1.0,
      "param_keep": 1.0,
      "graph_churn": 0.0,
      "param_churn": 0.0
    },
    {
      "epoch": 11,
      "loss": 1.9932951927185059,
      "task_loss": 1.9932951927185059,
      "train_acc": 0.26143792271614075,
      "val_acc": 0.24705882370471954,
      "test_acc": 0.2535947859287262,
      "best_val": 0.24705882370471954,
      "best_test": 0.2535947859287262,
      "temperature": 1.7594518710668834,
      "graph_keep": 1.0,
      "param_keep": 1.0,
      "graph_churn": 0.0,
      "param_churn": 0.0
    },
    {
      "epoch": 12,
      "loss": 1.9855320453643799,
      "task_loss": 1.9855320453643799,
      "train_acc": 0.26143792271614075,
      "val_acc": 0.24705882370471954,
      "test_acc": 0.2535947859287262,
      "best_val": 0.24705882370471954,
      "best_test": 0.2535947859287262,
      "temperature": 1.7390740061650933,
      "graph_keep": 1.0,
      "param_keep": 1.0,
      "graph_churn": 0.0,
      "param_churn": 0.0
    },
    {
      "epoch": 13,
      "loss": 1.9753141403198242,
      "task_loss": 1.9753141403198242,
      "train_acc": 0.26143792271614075,
      "val_acc": 0.24705882370471954,
      "test_acc": 0.2535947859287262,
      "best_val": 0.24705882370471954,
      "best_test": 0.2535947859287262,
      "temperature": 1.718932156459163,
      "graph_keep": 1.0,
      "param_keep": 1.0,
      "graph_churn": 0.0,
      "param_churn": 0.0
    },
    {
      "epoch": 14,
      "loss": 1.967861533164978,
      "task_loss": 1.967861533164978,
      "train_acc": 0.26143792271614075,
      "val_acc": 0.24705882370471954,
      "test_acc": 0.2535947859287262,
      "best_val": 0.24705882370471954,
      "best_test": 0.2535947859287262,
      "temperature": 1.6990235884354028,
      "graph_keep": 1.0,
      "param_keep": 1.0,
      "graph_churn": 0.0,
      "param_churn": 0.0
    },
    {
      "epoch": 15,
      "loss": 1.9635884761810303,
      "task_loss": 1.9635884761810303,
      "train_acc": 0.26143792271614075,
      "val_acc": 0.24705882370471954,
      "test_acc": 0.2535947859287262,
      "best_val": 0.24705882370471954,
      "best_test": 0.2535947859287262,
      "temperature": 1.6793456002395126,
      "graph_keep": 0.9971428513526917,
      "param_keep": 0.9971428513526917,
      "graph_churn": 0.0028571486473083496,
      "param_churn": 0.0028571486473083496
    },
    {
      "epoch": 16,
      "loss": 1.9547038078308105,
      "task_loss": 1.9547038078308105,
      "train_acc": 0.26143792271614075,
      "val_acc": 0.24705882370471954,
      "test_acc": 0.2535947859287262,
      "best_val": 0.24705882370471954,
      "best_test": 0.2535947859287262,
      "temperature": 1.6598955213099051,
      "graph_keep": 0.9942855834960938,
      "param_keep": 0.9942857027053833,
      "graph_churn": 0.0028572678565979004,
      "param_churn": 0.0028571486473083496
    },
    {
      "epoch": 17,
      "loss": 1.9532389640808105,
      "task_loss": 1.9532389640808105,
      "train_acc": 0.26143792271614075,
      "val_acc": 0.24705882370471954,
      "test_acc": 0.2535947859287262,
      "best_val": 0.24705882370471954,
      "best_test": 0.2535947859287262,
      "temperature": 1.640670712015276,
      "graph_keep": 0.991428554058075,
      "param_keep": 0.991428554058075,
      "graph_churn": 0.002857029205188155,
      "param_churn": 0.0028571486473083496
    },
    {
      "epoch": 18,
      "loss": 1.9445240497589111,
      "task_loss": 1.9445240497589111,
      "train_acc": 0.26143792271614075,
      "val_acc": 0.24705882370471954,
      "test_acc": 0.2535947859287262,
      "best_val": 0.24705882370471954,
      "best_test": 0.2535947859287262,
      "temperature": 1.6216685632963697,
      "graph_keep": 0.9885713458061218,
      "param_keep": 0.9885714054107666,
      "graph_churn": 0.0028572678565979004,
      "param_churn": 0.0028571486473083496
    },
    {
      "epoch": 19,
      "loss": 1.9459316730499268,
      "task_loss": 1.9459316730499268,
      "train_acc": 0.26143792271614075,
      "val_acc": 0.24705882370471954,
      "test_acc": 0.2535947859287262,
      "best_val": 0.24705882370471954,
      "best_test": 0.2535947859287262,
      "temperature": 1.6028864963118972,
      "graph_keep": 0.985714316368103,
      "param_keep": 0.985714316368103,
      "graph_churn": 0.002857029205188155,
      "param_churn": 0.0028571421280503273
    },
    {
      "epoch": 20,
      "loss": 1.9406263828277588,
      "task_loss": 1.9406263828277588,
      "train_acc": 0.26143792271614075,
      "val_acc": 0.24705882370471954,
      "test_acc": 0.2535947859287262,
      "best_val": 0.24705882370471954,
      "best_test": 0.2535947859287262,
      "temperature": 1.5843219620885534,
      "graph_keep": 0.9828571677207947,
      "param_keep": 0.9828572273254395,
      "graph_churn": 0.0028571486473083496,
      "param_churn": 0.0028570955619215965
    },
    {
      "epoch": 21,
      "loss": 1.937111496925354,
      "task_loss": 1.937111496925354,
      "train_acc": 0.26143792271614075,
      "val_acc": 0.24705882370471954,
      "test_acc": 0.2535947859287262,
      "best_val": 0.24705882370471954,
      "best_test": 0.2535947859287262,
      "temperature": 1.565972441175087,
      "graph_keep": 0.9799998998641968,
      "param_keep": 0.9799999594688416,
      "graph_churn": 0.002857208251953125,
      "param_churn": 0.0028571998700499535
    },
    {
      "epoch": 22,
      "loss": 1.9332364797592163,
      "task_loss": 1.9332364797592163,
      "train_acc": 0.26143792271614075,
      "val_acc": 0.24705882370471954,
      "test_acc": 0.2535947859287262,
      "best_val": 0.24705882370471954,
      "best_test": 0.2535947859287262,
      "temperature": 1.5478354433003785,
      "graph_keep": 0.9771428108215332,
      "param_keep": 0.9771428108215332,
      "graph_churn": 0.002857089275494218,
      "param_churn": 0.0028571709990501404
    },
    {
      "epoch": 23,
      "loss": 1.9326708316802979,
      "task_loss": 1.9326708316802979,
      "train_acc": 0.26143792271614075,
      "val_acc": 0.24705882370471954,
      "test_acc": 0.2535947859287262,
      "best_val": 0.24705882370471954,
      "best_test": 0.2535947859287262,
      "temperature": 1.529908507035477,
      "graph_keep": 0.9742857813835144,
      "param_keep": 0.9742857217788696,
      "graph_churn": 0.002857089275494218,
      "param_churn": 0.0028570834547281265
    },
    {
      "epoch": 24,
      "loss": 1.9275169372558594,
      "task_loss": 1.9275169372558594,
      "train_acc": 0.26143792271614075,
      "val_acc": 0.24705882370471954,
      "test_acc": 0.2535947859287262,
      "best_val": 0.24705882370471954,
      "best_test": 0.2535947859287262,
      "temperature": 1.5121891994595535,
      "graph_keep": 0.9714285731315613,
      "param_keep": 0.9714285731315613,
      "graph_churn": 0.002857208251953125,
      "param_churn": 0.0028572045266628265
    },
    {
      "epoch": 25,
      "loss": 1.9231417179107666,
      "task_loss": 1.9231417179107666,
      "train_acc": 0.26143792271614075,
      "val_acc": 0.24705882370471954,
      "test_acc": 0.2535947859287262,
      "best_val": 0.24705882370471954,
      "best_test": 0.2535947859287262,
      "temperature": 1.4946751158297198,
      "graph_keep": 0.9685714840888977,
      "param_keep": 0.9685715436935425,
      "graph_churn": 0.0028571486473083496,
      "param_churn": 0.002857048064470291
    },
    {
      "epoch": 26,
      "loss": 1.9210898876190186,
      "task_loss": 1.9210898876190186,
      "train_acc": 0.26143792271614075,
      "val_acc": 0.24705882370471954,
      "test_acc": 0.2535947859287262,
      "best_val": 0.24705882370471954,
      "best_test": 0.2535947859287262,
      "temperature": 1.4773638792546744,
      "graph_keep": 0.9657142758369446,
      "param_keep": 0.9657142758369446,
      "graph_churn": 0.0028570913709700108,
      "param_churn": 0.0028572333976626396
    },
    {
      "epoch": 27,
      "loss": 1.9147281646728516,
      "task_loss": 1.9147281646728516,
      "train_acc": 0.26143792271614075,
      "val_acc": 0.24705882370471954,
      "test_acc": 0.2535947859287262,
      "best_val": 0.24705882370471954,
      "best_test": 0.2535947859287262,
      "temperature": 1.4602531403721262,
      "graph_keep": 0.9628571271896362,
      "param_keep": 0.9628571271896362,
      "graph_churn": 0.0028572066221386194,
      "param_churn": 0.0028570815920829773
    },
    {
      "epoch": 28,
      "loss": 1.910239577293396,
      "task_loss": 1.910239577293396,
      "train_acc": 0.26143792271614075,
      "val_acc": 0.24705882370471954,
      "test_acc": 0.2535947859287262,
      "best_val": 0.24705882370471954,
      "best_test": 0.2535947859287262,
      "temperature": 1.4433405770299566,
      "graph_keep": 0.9599999785423279,
      "param_keep": 0.9599999785423279,
      "graph_churn": 0.002857139566913247,
      "param_churn": 0.0028570862486958504
    },
    {
      "epoch": 29,
      "loss": 1.9067679643630981,
      "task_loss": 1.9067679643630981,
      "train_acc": 0.26143792271614075,
      "val_acc": 0.24705882370471954,
      "test_acc": 0.2535947859287262,
      "best_val": 0.24705882370471954,
      "best_test": 0.2535947859287262,
      "temperature": 1.426623893971071,
      "graph_keep": 0.9571427702903748,
      "param_keep": 0.9571428894996643,
      "graph_churn": 0.0028572105802595615,
      "param_churn": 0.0028573395684361458
    },
    {
      "epoch": 30,
      "loss": 1.9002629518508911,
      "task_loss": 1.9002629518508911,
      "train_acc": 0.26143792271614075,
      "val_acc": 0.24705882370471954,
      "test_acc": 0.2535947859287262,
      "best_val": 0.24705882370471954,
      "best_test": 0.2535947859287262,
      "temperature": 1.4101008225219043,
      "graph_keep": 0.954285740852356,
      "param_keep": 0.954285740852356,
      "graph_churn": 0.0028569765854626894,
      "param_churn": 0.0028569940477609634
    },
    {
      "epoch": 31,
      "loss": 1.8958405256271362,
      "task_loss": 1.8958405256271362,
      "train_acc": 0.26143792271614075,
      "val_acc": 0.24705882370471954,
      "test_acc": 0.2535947859287262,
      "best_val": 0.24705882370471954,
      "best_test": 0.2535947859287262,
      "temperature": 1.3937691202845306,
      "graph_keep": 0.9514284729957581,
      "param_keep": 0.9514285326004028,
      "graph_churn": 0.002857266226783395,
      "param_churn": 0.0028571458533406258
    },
    {
      "epoch": 32,
      "loss": 1.8907686471939087,
      "task_loss": 1.8907686471939087,
      "train_acc": 0.26143792271614075,
      "val_acc": 0.24705882370471954,
      "test_acc": 0.2535947859287262,
      "best_val": 0.24705882370471954,
      "best_test": 0.2535947859287262,
      "temperature": 1.377626570832341,
      "graph_keep": 0.9485713839530945,
      "param_keep": 0.9485714435577393,
      "graph_churn": 0.0028571474831551313,
      "param_churn": 0.0028571980074048042
    },
    {
      "epoch": 33,
      "loss": 1.8883953094482422,
      "task_loss": 1.8883953094482422,
      "train_acc": 0.26143792271614075,
      "val_acc": 0.24705882370471954,
      "test_acc": 0.2535947859287262,
      "best_val": 0.24705882370471954,
      "best_test": 0.2535947859287262,
      "temperature": 1.3616709834092449,
      "graph_keep": 0.9457143545150757,
      "param_keep": 0.9457142949104309,
      "graph_churn": 0.0028569104615598917,
      "param_churn": 0.002857135608792305
    },
    {
      "epoch": 34,
      "loss": 1.8820041418075562,
      "task_loss": 1.8820041418075562,
      "train_acc": 0.26143792271614075,
      "val_acc": 0.24705882370471954,
      "test_acc": 0.2535947859287262,
      "best_val": 0.24705882370471954,
      "best_test": 0.2535947859287262,
      "temperature": 1.3459001926323562,
      "graph_keep": 0.9428570866584778,
      "param_keep": 0.9428572058677673,
      "graph_churn": 0.0028573921881616116,
      "param_churn": 0.002857106737792492
    },
    {
      "epoch": 35,
      "loss": 1.8738995790481567,
      "task_loss": 1.8738995790481567,
      "train_acc": 0.26143792271614075,
      "val_acc": 0.24705882370471954,
      "test_acc": 0.2535947859287262,
      "best_val": 0.24705882370471954,
      "best_test": 0.2535947859287262,
      "temperature": 1.330312058198122,
      "graph_keep": 0.940000057220459,
      "param_keep": 0.940000057220459,
      "graph_churn": 0.0028570189606398344,
      "param_churn": 0.0028570974245667458
    },
    {
      "epoch": 36,
      "loss": 1.8698569536209106,
      "task_loss": 1.8698569536209106,
      "train_acc": 0.26143792271614075,
      "val_acc": 0.24705882370471954,
      "test_acc": 0.2535947859287262,
      "best_val": 0.24705882370471954,
      "best_test": 0.2535947859287262,
      "temperature": 1.3149044645918557,
      "graph_keep": 0.9371428489685059,
      "param_keep": 0.9371429085731506,
      "graph_churn": 0.0028571030125021935,
      "param_churn": 0.002857072278857231
    },
    {
      "epoch": 37,
      "loss": 1.8674824237823486,
      "task_loss": 1.8674824237823486,
      "train_acc": 0.26143792271614075,
      "val_acc": 0.24705882370471954,
      "test_acc": 0.2535947859287262,
      "best_val": 0.24705882370471954,
      "best_test": 0.2535947859287262,
      "temperature": 1.2996753208006329,
      "graph_keep": 0.9342857003211975,
      "param_keep": 0.9342857003211975,
      "graph_churn": 0.0028573269955813885,
      "param_churn": 0.0028572622686624527
    },
    {
      "epoch": 38,
      "loss": 1.8597257137298584,
      "task_loss": 1.8597257137298584,
      "train_acc": 0.26143792271614075,
      "val_acc": 0.24705882370471954,
      "test_acc": 0.2535947859287262,
      "best_val": 0.24705882370471954,
      "best_test": 0.2535947859287262,
      "temperature": 1.284622560029515,
      "graph_keep": 0.9314284920692444,
      "param_keep": 0.9314286708831787,
      "graph_churn": 0.0028571360744535923,
      "param_churn": 0.0028571514412760735
    },
    {
      "epoch": 39,
      "loss": 1.854499340057373,
      "task_loss": 1.854499340057373,
      "train_acc": 0.26143792271614075,
      "val_acc": 0.24705882370471954,
      "test_acc": 0.2535947859287262,
      "best_val": 0.24705882370471954,
      "best_test": 0.2535947859287262,
      "temperature": 1.269744139421056,
      "graph_keep": 0.9285715222358704,
      "param_keep": 0.9285714030265808,
      "graph_churn": 0.002857024082913995,
      "param_churn": 0.002857075072824955
    },
    {
      "epoch": 40,
      "loss": 1.8470841646194458,
      "task_loss": 1.8470841646194458,
      "train_acc": 0.26143792271614075,
      "val_acc": 0.24836601316928864,
      "test_acc": 0.2535947859287262,
      "best_val": 0.24836601316928864,
      "best_test": 0.2535947859287262,
      "temperature": 1.2550380397780618,
      "graph_keep": 0.9257143139839172,
      "param_keep": 0.925714373588562,
      "graph_churn": 0.002857081824913621,
      "param_churn": 0.0028572464361786842
    },
    {
      "epoch": 41,
      "loss": 1.8413552045822144,
      "task_loss": 1.8413552045822144,
      "train_acc": 0.26143792271614075,
      "val_acc": 0.24836601316928864,
      "test_acc": 0.2535947859287262,
      "best_val": 0.24836601316928864,
      "best_test": 0.2535947859287262,
      "temperature": 1.2405022652895579,
      "graph_keep": 0.9228571653366089,
      "param_keep": 0.9228571653366089,
      "graph_churn": 0.00285714422352612,
      "param_churn": 0.002857111394405365
    },
    {
      "epoch": 42,
      "loss": 1.830999493598938,
      "task_loss": 1.830999493598938,
      "train_acc": 0.26143792271614075,
      "val_acc": 0.24836601316928864,
      "test_acc": 0.2535947859287262,
      "best_val": 0.24836601316928864,
      "best_test": 0.2535947859287262,
      "temperature": 1.2261348432599306,
      "graph_keep": 0.9200000166893005,
      "param_keep": 0.9200000762939453,
      "graph_churn": 0.0028571609873324633,
      "param_churn": 0.002857132814824581
    },
    {
      "epoch": 43,
      "loss": 1.826850175857544,
      "task_loss": 1.826850175857544,
      "train_acc": 0.26274511218070984,
      "val_acc": 0.24836601316928864,
      "test_acc": 0.2535947859287262,
      "best_val": 0.24836601316928864,
      "best_test": 0.2535947859287262,
      "temperature": 1.2119338238412083,
      "graph_keep": 0.9171428084373474,
      "param_keep": 0.9171428680419922,
      "graph_churn": 0.002857264131307602,
      "param_churn": 0.0028571421280503273
    },
    {
      "epoch": 44,
      "loss": 1.8194113969802856,
      "task_loss": 1.8194113969802856,
      "train_acc": 0.26405230164527893,
      "val_acc": 0.24967320263385773,
      "test_acc": 0.25375819206237793,
      "best_val": 0.24967320263385773,
      "best_test": 0.25375819206237793,
      "temperature": 1.1978972797684395,
      "graph_keep": 0.9142856597900391,
      "param_keep": 0.9142857193946838,
      "graph_churn": 0.002857115352526307,
      "param_churn": 0.0028570732101798058
    },
    {
      "epoch": 45,
      "loss": 1.8108384609222412,
      "task_loss": 1.8108384609222412,
      "train_acc": 0.2679738700389862,
      "val_acc": 0.2535947859287262,
      "test_acc": 0.2553921639919281,
      "best_val": 0.2535947859287262,
      "best_test": 0.2553921639919281,
      "temperature": 1.1840233060981389,
      "graph_keep": 0.9114286303520203,
      "param_keep": 0.9114285111427307,
      "graph_churn": 0.00285708112642169,
      "param_churn": 0.002857208251953125
    },
    {
      "epoch": 46,
      "loss": 1.803231120109558,
      "task_loss": 1.803231120109558,
      "train_acc": 0.2718954384326935,
      "val_acc": 0.2549019753932953,
      "test_acc": 0.25833335518836975,
      "best_val": 0.2549019753932953,
      "best_test": 0.25833335518836975,
      "temperature": 1.1703100199497611,
      "graph_keep": 0.9085714221000671,
      "param_keep": 0.9085714817047119,
      "graph_churn": 0.0028571179136633873,
      "param_churn": 0.0028571197763085365
    },
    {
      "epoch": 47,
      "loss": 1.7955292463302612,
      "task_loss": 1.7955292463302612,
      "train_acc": 0.2849673330783844,
      "val_acc": 0.26405230164527893,
      "test_acc": 0.26862746477127075,
      "best_val": 0.26405230164527893,
      "best_test": 0.26862746477127075,
      "temperature": 1.1567555602501696,
      "graph_keep": 0.9057142734527588,
      "param_keep": 0.9057142734527588,
      "graph_churn": 0.0028572382871061563,
      "param_churn": 0.0028571784496307373
    },
    {
      "epoch": 48,
      "loss": 1.784706711769104,
      "task_loss": 1.784706711769104,
      "train_acc": 0.29281046986579895,
      "val_acc": 0.265359491109848,
      "test_acc": 0.2751634120941162,
      "best_val": 0.265359491109848,
      "best_test": 0.2751634120941162,
      "temperature": 1.1433580874810627,
      "graph_keep": 0.9028571248054504,
      "param_keep": 0.9028571248054504,
      "graph_churn": 0.002857111394405365,
      "param_churn": 0.002857164479792118
    },
    {
      "epoch": 49,
      "loss": 1.7755444049835205,
      "task_loss": 1.7755444049835205,
      "train_acc": 0.3019607961177826,
      "val_acc": 0.2679738700389862,
      "test_acc": 0.2826797366142273,
      "best_val": 0.2679738700389862,
      "best_test": 0.2826797366142273,
      "temperature": 1.1301157834293298,
      "graph_keep": 0.8999999761581421,
      "param_keep": 0.8999999761581421,
      "graph_churn": 0.0028571737930178642,
      "param_churn": 0.002857181243598461
    },
    {
      "epoch": 50,
      "loss": 1.772731900215149,
      "task_loss": 1.772731900215149,
      "train_acc": 0.30849674344062805,
      "val_acc": 0.27581700682640076,
      "test_acc": 0.2916666865348816,
      "best_val": 0.27581700682640076,
      "best_test": 0.2916666865348816,
      "temperature": 1.1170268509402932,
      "graph_keep": 0.897142767906189,
      "param_keep": 0.897142767906189,
      "graph_churn": 0.002857072278857231,
      "param_churn": 0.002857096493244171
    },
    {
      "epoch": 51,
      "loss": 1.7597421407699585,
      "task_loss": 1.7597421407699585,
      "train_acc": 0.3189542591571808,
      "val_acc": 0.29281046986579895,
      "test_acc": 0.3106209337711334,
      "best_val": 0.29281046986579895,
      "best_test": 0.3106209337711334,
      "temperature": 1.1040895136738125,
      "graph_keep": 0.8942857384681702,
      "param_keep": 0.8942857384681702,
      "graph_churn": 0.0028571714647114277,
      "param_churn": 0.0028571095317602158
    },
    {
      "epoch": 52,
      "loss": 1.7545084953308105,
      "task_loss": 1.7545084953308105,
      "train_acc": 0.3464052379131317,
      "val_acc": 0.3150326907634735,
      "test_acc": 0.34297385811805725,
      "best_val": 0.3150326907634735,
      "best_test": 0.34297385811805725,
      "temperature": 1.09130201586321,
      "graph_keep": 0.8914285898208618,
      "param_keep": 0.8914286494255066,
      "graph_churn": 0.002857150975614786,
      "param_churn": 0.0028571542352437973
    },
    {
      "epoch": 53,
      "loss": 1.7416483163833618,
      "task_loss": 1.7416483163833618,
      "train_acc": 0.36993464827537537,
      "val_acc": 0.3477124273777008,
      "test_acc": 0.36405229568481445,
      "best_val": 0.3477124273777008,
      "best_test": 0.36405229568481445,
      "temperature": 1.0786626220769924,
      "graph_keep": 0.8885714411735535,
      "param_keep": 0.8885715007781982,
      "graph_churn": 0.0028571526054292917,
      "param_churn": 0.002857116051018238
    },
    {
      "epoch": 54,
      "loss": 1.7336595058441162,
      "task_loss": 1.7336595058441162,
      "train_acc": 0.37516340613365173,
      "val_acc": 0.3607843220233917,
      "test_acc": 0.37205883860588074,
      "best_val": 0.3607843220233917,
      "best_test": 0.37205883860588074,
      "temperature": 1.0661696169833283,
      "graph_keep": 0.8857142925262451,
      "param_keep": 0.8857142925262451,
      "graph_churn": 0.0028570392169058323,
      "param_churn": 0.002857176586985588
    },
    {
      "epoch": 55,
      "loss": 1.7276082038879395,
      "task_loss": 1.7276082038879395,
      "train_acc": 0.3764705955982208,
      "val_acc": 0.3607843220233917,
      "test_acc": 0.3727124333381653,
      "best_val": 0.3607843220233917,
      "best_test": 0.37205883860588074,
      "temperature": 1.0538213051172554,
      "graph_keep": 0.882857084274292,
      "param_keep": 0.882857084274292,
      "graph_churn": 0.0028572804294526577,
      "param_churn": 0.002857087180018425
    },
    {
      "epoch": 56,
      "loss": 1.7192778587341309,
      "task_loss": 1.7192778587341309,
      "train_acc": 0.3830065429210663,
      "val_acc": 0.3673202693462372,
      "test_acc": 0.3785947859287262,
      "best_val": 0.3673202693462372,
      "best_test": 0.3785947859287262,
      "temperature": 1.0416160106505838,
      "graph_keep": 0.8800000548362732,
      "param_keep": 0.8799999952316284,
      "graph_churn": 0.0028571386355906725,
      "param_churn": 0.0028571905568242073
    },
    {
      "epoch": 57,
      "loss": 1.707552433013916,
      "task_loss": 1.707552433013916,
      "train_acc": 0.3986928164958954,
      "val_acc": 0.38562092185020447,
      "test_acc": 0.3919934630393982,
      "best_val": 0.38562092185020447,
      "best_test": 0.3919934630393982,
      "temperature": 1.0295520771644644,
      "graph_keep": 0.8771428465843201,
      "param_keep": 0.8771428465843201,
      "graph_churn": 0.0028571344446390867,
      "param_churn": 0.002857118844985962
    },
    {
      "epoch": 58,
      "loss": 1.701820969581604,
      "task_loss": 1.701820969581604,
      "train_acc": 0.4091503322124481,
      "val_acc": 0.40522876381874084,
      "test_acc": 0.40931373834609985,
      "best_val": 0.40522876381874084,
      "best_test": 0.40931373834609985,
      "temperature": 1.0176278674245909,
      "graph_keep": 0.8742856383323669,
      "param_keep": 0.8742856979370117,
      "graph_churn": 0.002857011975720525,
      "param_churn": 0.0028572361916303635
    },
    {
      "epoch": 59,
      "loss": 1.690002679824829,
      "task_loss": 1.690002679824829,
      "train_acc": 0.4117647111415863,
      "val_acc": 0.40130719542503357,
      "test_acc": 0.4122548997402191,
      "best_val": 0.40522876381874084,
      "best_test": 0.40931373834609985,
      "temperature": 1.0058417631590046,
      "graph_keep": 0.8714285492897034,
      "param_keep": 0.8714285492897034,
      "graph_churn": 0.0028572275768965483,
      "param_churn": 0.0028570862486958504
    },
    {
      "epoch": 60,
      "loss": 1.683829426765442,
      "task_loss": 1.683829426765442,
      "train_acc": 0.4104575216770172,
      "val_acc": 0.3947712481021881,
      "test_acc": 0.40261438488960266,
      "best_val": 0.40522876381874084,
      "best_test": 0.40931373834609985,
      "temperature": 0.9941921648384756,
      "graph_keep": 0.8685715198516846,
      "param_keep": 0.868571400642395,
      "graph_churn": 0.0028571614529937506,
      "param_churn": 0.0028571411967277527
    },
    {
      "epoch": 61,
      "loss": 1.6745818853378296,
      "task_loss": 1.6745818853378296,
      "train_acc": 0.4156862795352936,
      "val_acc": 0.3960784375667572,
      "test_acc": 0.41062092781066895,
      "best_val": 0.40522876381874084,
      "best_test": 0.40931373834609985,
      "temperature": 0.9826774914594238,
      "graph_keep": 0.8657143115997314,
      "param_keep": 0.8657143115997314,
      "graph_churn": 0.0028571076691150665,
      "param_churn": 0.0028570247814059258
    },
    {
      "epoch": 62,
      "loss": 1.668445348739624,
      "task_loss": 1.668445348739624,
      "train_acc": 0.4248366057872772,
      "val_acc": 0.4091503322124481,
      "test_acc": 0.41862747073173523,
      "best_val": 0.4091503322124481,
      "best_test": 0.41862747073173523,
      "temperature": 0.9712961803293572,
      "graph_keep": 0.8628571629524231,
      "param_keep": 0.8628571629524231,
      "graph_churn": 0.002857176586985588,
      "param_churn": 0.002857167273759842
    },
    {
      "epoch": 63,
      "loss": 1.656827449798584,
      "task_loss": 1.656827449798584,
      "train_acc": 0.43529412150382996,
      "val_acc": 0.41960784792900085,
      "test_acc": 0.42777779698371887,
      "best_val": 0.41960784792900085,
      "best_test": 0.42777779698371887,
      "temperature": 0.9600466868547932,
      "graph_keep": 0.8600000143051147,
      "param_keep": 0.8600000143051147,
      "graph_churn": 0.0028571428265422583,
      "param_churn": 0.002857152372598648
    },
    {
      "epoch": 64,
      "loss": 1.6489460468292236,
      "task_loss": 1.6489460468292236,
      "train_acc": 0.4444444477558136,
      "val_acc": 0.43660131096839905,
      "test_acc": 0.443464070558548,
      "best_val": 0.43660131096839905,
      "best_test": 0.443464070558548,
      "temperature": 0.9489274843316374,
      "graph_keep": 0.8571428060531616,
      "param_keep": 0.8571428656578064,
      "graph_churn": 0.0028571279253810644,
      "param_churn": 0.002857138402760029
    },
    {
      "epoch": 65,
      "loss": 1.6415894031524658,
      "task_loss": 1.6415894031524658,
      "train_acc": 0.4483660161495209,
      "val_acc": 0.43398693203926086,
      "test_acc": 0.4398692846298218,
      "best_val": 0.43660131096839905,
      "best_test": 0.443464070558548,
      "temperature": 0.9379370637379897,
      "graph_keep": 0.8542856574058533,
      "param_keep": 0.8542856574058533,
      "graph_churn": 0.00285715633071959,
      "param_churn": 0.0028572184965014458
    },
    {
      "epoch": 66,
      "loss": 1.6313745975494385,
      "task_loss": 1.6313745975494385,
      "train_acc": 0.4575163424015045,
      "val_acc": 0.43529412150382996,
      "test_acc": 0.4444444477558136,
      "best_val": 0.43660131096839905,
      "best_test": 0.443464070558548,
      "temperature": 0.9270739335293499,
      "graph_keep": 0.8514286279678345,
      "param_keep": 0.8514286279678345,
      "graph_churn": 0.0028571549337357283,
      "param_churn": 0.002857164479792118
    },
    {
      "epoch": 67,
      "loss": 1.6212048530578613,
      "task_loss": 1.6212048530578613,
      "train_acc": 0.46928104758262634,
      "val_acc": 0.4405228793621063,
      "test_acc": 0.4534313976764679,
      "best_val": 0.4405228793621063,
      "best_test": 0.4534313976764679,
      "temperature": 0.9163366194361962,
      "graph_keep": 0.8485714793205261,
      "param_keep": 0.8485714197158813,
      "graph_churn": 0.002857138402760029,
      "param_churn": 0.0028571579605340958
    },
    {
      "epoch": 68,
      "loss": 1.6125385761260986,
      "task_loss": 1.6125385761260986,
      "train_acc": 0.47058823704719543,
      "val_acc": 0.4405228793621063,
      "test_acc": 0.45898693799972534,
      "best_val": 0.4405228793621063,
      "best_test": 0.4534313976764679,
      "temperature": 0.9057236642639067,
      "graph_keep": 0.8457142114639282,
      "param_keep": 0.8457142114639282,
      "graph_churn": 0.0028571810107678175,
      "param_churn": 0.0028571048751473427
    },
    {
      "epoch": 69,
      "loss": 1.6052814722061157,
      "task_loss": 1.6052814722061157,
      "train_acc": 0.47843137383461,
      "val_acc": 0.4457516372203827,
      "test_acc": 0.46388891339302063,
      "best_val": 0.4457516372203827,
      "best_test": 0.46388891339302063,
      "temperature": 0.8952336276949993,
      "graph_keep": 0.8428570628166199,
      "param_keep": 0.8428570628166199,
      "graph_churn": 0.0028571775183081627,
      "param_churn": 0.0028571663424372673
    },
    {
      "epoch": 70,
      "loss": 1.5982269048690796,
      "task_loss": 1.5982269048690796,
      "train_acc": 0.48235294222831726,
      "val_acc": 0.45228758454322815,
      "test_acc": 0.4723856449127197,
      "best_val": 0.45228758454322815,
      "best_test": 0.4723856449127197,
      "temperature": 0.8848650860936618,
      "graph_keep": 0.8399999737739563,
      "param_keep": 0.8399999141693115,
      "graph_churn": 0.00285701104439795,
      "param_churn": 0.0028571784496307373
    },
    {
      "epoch": 71,
      "loss": 1.5905498266220093,
      "task_loss": 1.5905498266220093,
      "train_acc": 0.4941176474094391,
      "val_acc": 0.4562091529369354,
      "test_acc": 0.475326806306839,
      "best_val": 0.4562091529369354,
      "best_test": 0.475326806306839,
      "temperature": 0.8746166323125456,
      "graph_keep": 0.8371428847312927,
      "param_keep": 0.8371429443359375,
      "graph_churn": 0.0028570820577442646,
      "param_churn": 0.002857023850083351
    },
    {
      "epoch": 72,
      "loss": 1.580409288406372,
      "task_loss": 1.580409288406372,
      "train_acc": 0.49673202633857727,
      "val_acc": 0.4575163424015045,
      "test_acc": 0.4799019694328308,
      "best_val": 0.4575163424015045,
      "best_test": 0.4799019694328308,
      "temperature": 0.8644868755017974,
      "graph_keep": 0.8342856764793396,
      "param_keep": 0.8342857360839844,
      "graph_churn": 0.0028571507427841425,
      "param_churn": 0.0028571393340826035
    },
    {
      "epoch": 73,
      "loss": 1.5711946487426758,
      "task_loss": 1.5711946487426758,
      "train_acc": 0.49803921580314636,
      "val_acc": 0.4601307213306427,
      "test_acc": 0.48676472902297974,
      "best_val": 0.4601307213306427,
      "best_test": 0.48676472902297974,
      "temperature": 0.8544744409203022,
      "graph_keep": 0.8314286470413208,
      "param_keep": 0.831428587436676,
      "graph_churn": 0.0028571789152920246,
      "param_churn": 0.0028571467846632004
    },
    {
      "epoch": 74,
      "loss": 1.5656044483184814,
      "task_loss": 1.5656044483184814,
      "train_acc": 0.49934640526771545,
      "val_acc": 0.4614379107952118,
      "test_acc": 0.48986929655075073,
      "best_val": 0.4614379107952118,
      "best_test": 0.48986929655075073,
      "temperature": 0.844577969749114,
      "graph_keep": 0.8285714387893677,
      "param_keep": 0.8285714387893677,
      "graph_churn": 0.0028571633156389,
      "param_churn": 0.002857184037566185
    },
    {
      "epoch": 75,
      "loss": 1.5593030452728271,
      "task_loss": 1.5593030452728271,
      "train_acc": 0.49803921580314636,
      "val_acc": 0.46405228972435,
      "test_acc": 0.4915032684803009,
      "best_val": 0.46405228972435,
      "best_test": 0.4915032684803009,
      "temperature": 0.8347961189070451,
      "graph_keep": 0.8257142901420593,
      "param_keep": 0.8257143497467041,
      "graph_churn": 0.0028572052251547575,
      "param_churn": 0.002857215702533722
    },
    {
      "epoch": 76,
      "loss": 1.5514289140701294,
      "task_loss": 1.5514289140701294,
      "train_acc": 0.501960813999176,
      "val_acc": 0.46666666865348816,
      "test_acc": 0.49346405267715454,
      "best_val": 0.46666666865348816,
      "best_test": 0.49346405267715454,
      "temperature": 0.8251275608683923,
      "graph_keep": 0.8228572010993958,
      "param_keep": 0.822857141494751,
      "graph_churn": 0.0028570941649377346,
      "param_churn": 0.0028570787981152534
    },
    {
      "epoch": 77,
      "loss": 1.5417466163635254,
      "task_loss": 1.5417466163635254,
      "train_acc": 0.5084967613220215,
      "val_acc": 0.46797385811805725,
      "test_acc": 0.4982026219367981,
      "best_val": 0.46797385811805725,
      "best_test": 0.4982026219367981,
      "temperature": 0.815570983482775,
      "graph_keep": 0.8200000524520874,
      "param_keep": 0.8200000524520874,
      "graph_churn": 0.0028571640141308308,
      "param_churn": 0.0028571700677275658
    },
    {
      "epoch": 78,
      "loss": 1.5336170196533203,
      "task_loss": 1.5336170196533203,
      "train_acc": 0.5071895718574524,
      "val_acc": 0.46928104758262634,
      "test_acc": 0.5024510025978088,
      "best_val": 0.46928104758262634,
      "best_test": 0.5024510025978088,
      "temperature": 0.806125089797059,
      "graph_keep": 0.8171429634094238,
      "param_keep": 0.8171427845954895,
      "graph_churn": 0.0028571425937116146,
      "param_churn": 0.002857135608792305
    },
    {
      "epoch": 79,
      "loss": 1.5287351608276367,
      "task_loss": 1.5287351608276367,
      "train_acc": 0.5058823823928833,
      "val_acc": 0.47058823704719543,
      "test_acc": 0.5047385692596436,
      "best_val": 0.47058823704719543,
      "best_test": 0.5047385692596436,
      "temperature": 0.7967885978793422,
      "graph_keep": 0.8142856955528259,
      "param_keep": 0.8142856955528259,
      "graph_churn": 0.002857144456356764,
      "param_churn": 0.0028571244329214096
    },
    {
      "epoch": 80,
      "loss": 1.5200177431106567,
      "task_loss": 1.5200177431106567,
      "train_acc": 0.5084967613220215,
      "val_acc": 0.4718954265117645,
      "test_acc": 0.5091503262519836,
      "best_val": 0.4718954265117645,
      "best_test": 0.5091503262519836,
      "temperature": 0.78756024064498,
      "graph_keep": 0.8114285469055176,
      "param_keep": 0.8114285469055176,
      "graph_churn": 0.0028571481816470623,
      "param_churn": 0.0028571998700499535
    },
    {
      "epoch": 81,
      "loss": 1.5128376483917236,
      "task_loss": 1.5128376483917236,
      "train_acc": 0.5137255191802979,
      "val_acc": 0.4797385632991791,
      "test_acc": 0.5161764621734619,
      "best_val": 0.4797385632991791,
      "best_test": 0.5161764621734619,
      "temperature": 0.778438765684626,
      "graph_keep": 0.8085713982582092,
      "param_keep": 0.808571457862854,
      "graph_churn": 0.0028571186121553183,
      "param_churn": 0.0028571030125021935
    },
    {
      "epoch": 82,
      "loss": 1.4999452829360962,
      "task_loss": 1.4999452829360962,
      "train_acc": 0.5241830348968506,
      "val_acc": 0.49673202633857727,
      "test_acc": 0.5264706015586853,
      "best_val": 0.49673202633857727,
      "best_test": 0.5264706015586853,
      "temperature": 0.7694229350942623,
      "graph_keep": 0.8057143688201904,
      "param_keep": 0.8057143688201904,
      "graph_churn": 0.002857192885130644,
      "param_churn": 0.0028571411967277527
    },
    {
      "epoch": 83,
      "loss": 1.4992260932922363,
      "task_loss": 1.4992260932922363,
      "train_acc": 0.5320261716842651,
      "val_acc": 0.5045751929283142,
      "test_acc": 0.5339869260787964,
      "best_val": 0.5045751929283142,
      "best_test": 0.5339869260787964,
      "temperature": 0.7605115253072006,
      "graph_keep": 0.8028570413589478,
      "param_keep": 0.8028571009635925,
      "graph_churn": 0.002857040613889694,
      "param_churn": 0.0028571104630827904
    },
    {
      "epoch": 84,
      "loss": 1.4928536415100098,
      "task_loss": 1.4928536415100098,
      "train_acc": 0.5359477400779724,
      "val_acc": 0.5124183297157288,
      "test_acc": 0.5421568751335144,
      "best_val": 0.5124183297157288,
      "best_test": 0.5421568751335144,
      "temperature": 0.7517033269280274,
      "graph_keep": 0.8000000715255737,
      "param_keep": 0.8000000715255737,
      "graph_churn": 0.002857162617146969,
      "param_churn": 0.0028570927679538727
    },
    {
      "epoch": 85,
      "loss": 1.487259030342102,
      "task_loss": 1.487259030342102,
      "train_acc": 0.545098066329956,
      "val_acc": 0.5150327086448669,
      "test_acc": 0.5464052557945251,
      "best_val": 0.5150327086448669,
      "best_test": 0.5464052557945251,
      "temperature": 0.7429971445684742,
      "graph_keep": 0.7971428632736206,
      "param_keep": 0.7971429228782654,
      "graph_churn": 0.0028570883441716433,
      "param_churn": 0.0028571784496307373
    },
    {
      "epoch": 86,
      "loss": 1.475868821144104,
      "task_loss": 1.475868821144104,
      "train_acc": 0.5516340136528015,
      "val_acc": 0.516339898109436,
      "test_acc": 0.5495098233222961,
      "best_val": 0.516339898109436,
      "best_test": 0.5495098233222961,
      "temperature": 0.7343917966851865,
      "graph_keep": 0.7942856550216675,
      "param_keep": 0.7942857146263123,
      "graph_churn": 0.002857268089428544,
      "param_churn": 0.0028571300208568573
    },
    {
      "epoch": 87,
      "loss": 1.4719902276992798,
      "task_loss": 1.4719902276992798,
      "train_acc": 0.5529412031173706,
      "val_acc": 0.5137255191802979,
      "test_acc": 0.5496731996536255,
      "best_val": 0.516339898109436,
      "best_test": 0.5495098233222961,
      "temperature": 0.7258861154193733,
      "graph_keep": 0.7914285659790039,
      "param_keep": 0.7914285659790039,
      "graph_churn": 0.0028571863658726215,
      "param_churn": 0.0028572333976626396
    },
    {
      "epoch": 88,
      "loss": 1.4643027782440186,
      "task_loss": 1.4643027782440186,
      "train_acc": 0.5503268241882324,
      "val_acc": 0.5281046032905579,
      "test_acc": 0.5526143908500671,
      "best_val": 0.5281046032905579,
      "best_test": 0.5526143908500671,
      "temperature": 0.7174789464383134,
      "graph_keep": 0.7885713577270508,
      "param_keep": 0.7885714769363403,
      "graph_churn": 0.0028569786809384823,
      "param_churn": 0.0028571374714374542
    },
    {
      "epoch": 89,
      "loss": 1.4590660333633423,
      "task_loss": 1.4590660333633423,
      "train_acc": 0.5516340136528015,
      "val_acc": 0.5333333611488342,
      "test_acc": 0.5545752048492432,
      "best_val": 0.5333333611488342,
      "best_test": 0.5545752048492432,
      "temperature": 0.7091691487786974,
      "graph_keep": 0.7857141494750977,
      "param_keep": 0.7857142090797424,
      "graph_churn": 0.002857221057638526,
      "param_churn": 0.002857123501598835
    },
    {
      "epoch": 90,
      "loss": 1.4497243165969849,
      "task_loss": 1.4497243165969849,
      "train_acc": 0.558169960975647,
      "val_acc": 0.5411764979362488,
      "test_acc": 0.5637255311012268,
      "best_val": 0.5411764979362488,
      "best_test": 0.5637255311012268,
      "temperature": 0.7009555946917836,
      "graph_keep": 0.7828570604324341,
      "param_keep": 0.7828571796417236,
      "graph_churn": 0.0028571609873324633,
      "param_churn": 0.0028571374714374542
    },
    {
      "epoch": 91,
      "loss": 1.4411591291427612,
      "task_loss": 1.4411591291427612,
      "train_acc": 0.5633987188339233,
      "val_acc": 0.545098066329956,
      "test_acc": 0.570588231086731,
      "best_val": 0.545098066329956,
      "best_test": 0.570588231086731,
      "temperature": 0.6928371694903476,
      "graph_keep": 0.7800000309944153,
      "param_keep": 0.7799999713897705,
      "graph_churn": 0.002857271581888199,
      "param_churn": 0.002857212908565998
    },
    {
      "epoch": 92,
      "loss": 1.4348690509796143,
      "task_loss": 1.4348690509796143,
      "train_acc": 0.5751634240150452,
      "val_acc": 0.5542483925819397,
      "test_acc": 0.5795751810073853,
      "best_val": 0.5542483925819397,
      "best_test": 0.5795751810073853,
      "temperature": 0.6848127713974053,
      "graph_keep": 0.7771428227424622,
      "param_keep": 0.7771428823471069,
      "graph_churn": 0.0028569952119141817,
      "param_churn": 0.0028570378199219704
    },
    {
      "epoch": 93,
      "loss": 1.4300705194473267,
      "task_loss": 1.4300705194473267,
      "train_acc": 0.586928129196167,
      "val_acc": 0.5647059082984924,
      "test_acc": 0.5882353186607361,
      "best_val": 0.5647059082984924,
      "best_test": 0.5882353186607361,
      "temperature": 0.6768813113966865,
      "graph_keep": 0.7742857336997986,
      "param_keep": 0.774285614490509,
      "graph_churn": 0.002857167273759842,
      "param_churn": 0.0028571560978889465
    },
    {
      "epoch": 94,
      "loss": 1.426696538925171,
      "task_loss": 1.426696538925171,
      "train_acc": 0.586928129196167,
      "val_acc": 0.5673202872276306,
      "test_acc": 0.5893791317939758,
      "best_val": 0.5673202872276306,
      "best_test": 0.5893791317939758,
      "temperature": 0.6690417130848417,
      "graph_keep": 0.7714285850524902,
      "param_keep": 0.7714285850524902,
      "graph_churn": 0.002857162617146969,
      "param_churn": 0.002857164479792118
    },
    {
      "epoch": 95,
      "loss": 1.4214575290679932,
      "task_loss": 1.4214575290679932,
      "train_acc": 0.5908496975898743,
      "val_acc": 0.5673202872276306,
      "test_acc": 0.5915032625198364,
      "best_val": 0.5673202872276306,
      "best_test": 0.5893791317939758,
      "temperature": 0.6612929125253595,
      "graph_keep": 0.7685714364051819,
      "param_keep": 0.7685713768005371,
      "graph_churn": 0.002857150509953499,
      "param_churn": 0.002857126295566559
    },
    {
      "epoch": 96,
      "loss": 1.4170277118682861,
      "task_loss": 1.4170277118682861,
      "train_acc": 0.5960784554481506,
      "val_acc": 0.572549045085907,
      "test_acc": 0.5952614545822144,
      "best_val": 0.572549045085907,
      "best_test": 0.5952614545822144,
      "temperature": 0.6536338581041767,
      "graph_keep": 0.7657142281532288,
      "param_keep": 0.7657142877578735,
      "graph_churn": 0.002857005689293146,
      "param_churn": 0.0028571737930178642
    },
    {
      "epoch": 97,
      "loss": 1.4111392498016357,
      "task_loss": 1.4111392498016357,
      "train_acc": 0.6039215922355652,
      "val_acc": 0.5856209397315979,
      "test_acc": 0.6037582159042358,
      "best_val": 0.5856209397315979,
      "best_test": 0.6037582159042358,
      "temperature": 0.6460635103869607,
      "graph_keep": 0.7628571391105652,
      "param_keep": 0.7628570795059204,
      "graph_churn": 0.002857279498130083,
      "param_churn": 0.0028571011498570442
    },
    {
      "epoch": 98,
      "loss": 1.4051814079284668,
      "task_loss": 1.4051814079284668,
      "train_acc": 0.6183006763458252,
      "val_acc": 0.6052287817001343,
      "test_acc": 0.6174836754798889,
      "best_val": 0.6052287817001343,
      "best_test": 0.6174836754798889,
      "temperature": 0.638580841978044,
      "graph_keep": 0.7599999904632568,
      "param_keep": 0.7600000500679016,
      "graph_churn": 0.002857126295566559,
      "param_churn": 0.002857186831533909
    },
    {
      "epoch": 99,
      "loss": 1.39463210105896,
      "task_loss": 1.39463210105896,
      "train_acc": 0.6274510025978088,
      "val_acc": 0.6130719184875488,
      "test_acc": 0.6253268122673035,
      "best_val": 0.6130719184875488,
      "best_test": 0.6253268122673035,
      "temperature": 0.6311848373809934,
      "graph_keep": 0.7571429014205933,
      "param_keep": 0.7571427822113037,
      "graph_churn": 0.00285724806599319,
      "param_churn": 0.0028570936992764473
    },
    {
      "epoch": 100,
      "loss": 1.3969508409500122,
      "task_loss": 1.3969508409500122,
      "train_acc": 0.6326797604560852,
      "val_acc": 0.615686297416687,
      "test_acc": 0.6287581920623779,
      "best_val": 0.615686297416687,
      "best_test": 0.6287581920623779,
      "temperature": 0.6238744928607941,
      "graph_keep": 0.7542856931686401,
      "param_keep": 0.7542857527732849,
      "graph_churn": 0.002857053652405739,
      "param_churn": 0.0028571970760822296
    },
    {
      "epoch": 101,
      "loss": 1.3866764307022095,
      "task_loss": 1.3866764307022095,
      "train_acc": 0.6379085183143616,
      "val_acc": 0.6235294342041016,
      "test_acc": 0.6321895718574524,
      "best_val": 0.6235294342041016,
      "best_test": 0.6321895718574524,
      "temperature": 0.6166488163076292,
      "graph_keep": 0.7514285445213318,
      "param_keep": 0.751428484916687,
      "graph_churn": 0.0028571179136633873,
      "param_churn": 0.0028571439906954765
    },
    {
      "epoch": 102,
      "loss": 1.3817325830459595,
      "task_loss": 1.3817325830459595,
      "train_acc": 0.6483660340309143,
      "val_acc": 0.6248366236686707,
      "test_acc": 0.6377451419830322,
      "best_val": 0.6248366236686707,
      "best_test": 0.6377451419830322,
      "temperature": 0.6095068271022378,
      "graph_keep": 0.7485713958740234,
      "param_keep": 0.7485713958740234,
      "graph_churn": 0.0028570748399943113,
      "param_churn": 0.0028569968417286873
    },
    {
      "epoch": 103,
      "loss": 1.3779085874557495,
      "task_loss": 1.3779085874557495,
      "train_acc": 0.6535947918891907,
      "val_acc": 0.630065381526947,
      "test_acc": 0.6447712779045105,
      "best_val": 0.630065381526947,
      "best_test": 0.6447712779045105,
      "temperature": 0.6024475559828313,
      "graph_keep": 0.7457141876220703,
      "param_keep": 0.7457143068313599,
      "graph_churn": 0.00285721174441278,
      "param_churn": 0.0028571542352437973
    },
    {
      "epoch": 104,
      "loss": 1.3738595247268677,
      "task_loss": 1.3738595247268677,
      "train_acc": 0.6535947918891907,
      "val_acc": 0.6313725709915161,
      "test_acc": 0.6459150314331055,
      "best_val": 0.6313725709915161,
      "best_test": 0.6459150314331055,
      "temperature": 0.5954700449135529,
      "graph_keep": 0.7428571581840515,
      "param_keep": 0.7428570985794067,
      "graph_churn": 0.002857104642316699,
      "param_churn": 0.002857205457985401
    },
    {
      "epoch": 105,
      "loss": 1.3655799627304077,
      "task_loss": 1.3655799627304077,
      "train_acc": 0.6522876024246216,
      "val_acc": 0.6313725709915161,
      "test_acc": 0.6419934630393982,
      "best_val": 0.6313725709915161,
      "best_test": 0.6459150314331055,
      "temperature": 0.5885733469544588,
      "graph_keep": 0.7400000095367432,
      "param_keep": 0.7400000691413879,
      "graph_churn": 0.0028572322335094213,
      "param_churn": 0.0028571495786309242
    },
    {
      "epoch": 106,
      "loss": 1.3636529445648193,
      "task_loss": 1.3636529445648193,
      "train_acc": 0.6549019813537598,
      "val_acc": 0.6326797604560852,
      "test_acc": 0.6470588445663452,
      "best_val": 0.6326797604560852,
      "best_test": 0.6470588445663452,
      "temperature": 0.5817565261330063,
      "graph_keep": 0.7371429204940796,
      "param_keep": 0.73714280128479,
      "graph_churn": 0.002857098588719964,
      "param_churn": 0.0028571579605340958
    },
    {
      "epoch": 107,
      "loss": 1.3590408563613892,
      "task_loss": 1.3590408563613892,
      "train_acc": 0.6679738759994507,
      "val_acc": 0.6418300867080688,
      "test_acc": 0.6589869260787964,
      "best_val": 0.6418300867080688,
      "best_test": 0.6589869260787964,
      "temperature": 0.5750186573170298,
      "graph_keep": 0.734285831451416,
      "param_keep": 0.7342857122421265,
      "graph_churn": 0.002857200102880597,
      "param_churn": 0.0028571877628564835
    },
    {
      "epoch": 108,
      "loss": 1.356460690498352,
      "task_loss": 1.356460690498352,
      "train_acc": 0.6915032863616943,
      "val_acc": 0.6601307392120361,
      "test_acc": 0.6717320680618286,
      "best_val": 0.6601307392120361,
      "best_test": 0.6717320680618286,
      "temperature": 0.5683588260891884,
      "graph_keep": 0.7314286231994629,
      "param_keep": 0.7314286231994629,
      "graph_churn": 0.002856974955648184,
      "param_churn": 0.0028571682050824165
    },
    {
      "epoch": 109,
      "loss": 1.352455973625183,
      "task_loss": 1.352455973625183,
      "train_acc": 0.6967320442199707,
      "val_acc": 0.6705882549285889,
      "test_acc": 0.6799019575119019,
      "best_val": 0.6705882549285889,
      "best_test": 0.6799019575119019,
      "temperature": 0.5617761286228676,
      "graph_keep": 0.7285714149475098,
      "param_keep": 0.7285715341567993,
      "graph_churn": 0.002857242478057742,
      "param_churn": 0.0028571290895342827
    },
    {
      "epoch": 110,
      "loss": 1.3435966968536377,
      "task_loss": 1.3435966968536377,
      "train_acc": 0.6784313917160034,
      "val_acc": 0.657516360282898,
      "test_acc": 0.676960825920105,
      "best_val": 0.6705882549285889,
      "best_test": 0.6799019575119019,
      "temperature": 0.5552696715595177,
      "graph_keep": 0.7257142066955566,
      "param_keep": 0.7257143259048462,
      "graph_churn": 0.002857113489881158,
      "param_churn": 0.002857099287211895
    },
    {
      "epoch": 111,
      "loss": 1.3430169820785522,
      "task_loss": 1.3430169820785522,
      "train_acc": 0.6810457706451416,
      "val_acc": 0.6522876024246216,
      "test_acc": 0.676307201385498,
      "best_val": 0.6705882549285889,
      "best_test": 0.6799019575119019,
      "temperature": 0.5488385718874136,
      "graph_keep": 0.7228571772575378,
      "param_keep": 0.7228571176528931,
      "graph_churn": 0.0028572282753884792,
      "param_churn": 0.002857169136404991
    },
    {
      "epoch": 112,
      "loss": 1.336087703704834,
      "task_loss": 1.336087703704834,
      "train_acc": 0.6810457706451416,
      "val_acc": 0.6549019813537598,
      "test_acc": 0.6799019575119019,
      "best_val": 0.6705882549285889,
      "best_test": 0.6799019575119019,
      "temperature": 0.5424819568218185,
      "graph_keep": 0.7200000882148743,
      "param_keep": 0.7200000286102295,
      "graph_churn": 0.00285705947317183,
      "param_churn": 0.0028570974245667458
    },
    {
      "epoch": 113,
      "loss": 1.33870267868042,
      "task_loss": 1.33870267868042,
      "train_acc": 0.6875817179679871,
      "val_acc": 0.6653594970703125,
      "test_acc": 0.6846405267715454,
      "best_val": 0.6705882549285889,
      "best_test": 0.6799019575119019,
      "temperature": 0.5361989636865357,
      "graph_keep": 0.7171428799629211,
      "param_keep": 0.7171429395675659,
      "graph_churn": 0.0028570927679538727,
      "param_churn": 0.002857123501598835
    },
    {
      "epoch": 114,
      "loss": 1.326263666152954,
      "task_loss": 1.326263666152954,
      "train_acc": 0.6954248547554016,
      "val_acc": 0.6679738759994507,
      "test_acc": 0.6852941513061523,
      "best_val": 0.6705882549285889,
      "best_test": 0.6799019575119019,
      "temperature": 0.5299887397968317,
      "graph_keep": 0.7142856121063232,
      "param_keep": 0.714285671710968,
      "graph_churn": 0.002857198938727379,
      "param_churn": 0.0028571346774697304
    },
    {
      "epoch": 115,
      "loss": 1.3200559616088867,
      "task_loss": 1.3200559616088867,
      "train_acc": 0.6941176652908325,
      "val_acc": 0.6666666865348816,
      "test_acc": 0.6851307153701782,
      "best_val": 0.6705882549285889,
      "best_test": 0.6799019575119019,
      "temperature": 0.5238504423437159,
      "graph_keep": 0.7114286422729492,
      "param_keep": 0.7114285230636597,
      "graph_churn": 0.0028571602888405323,
      "param_churn": 0.0028722346760332584
    },
    {
      "epoch": 116,
      "loss": 1.3183462619781494,
      "task_loss": 1.3183462619781494,
      "train_acc": 0.6980392336845398,
      "val_acc": 0.673202633857727,
      "test_acc": 0.6911764740943909,
      "best_val": 0.673202633857727,
      "best_test": 0.6911764740943909,
      "temperature": 0.5177832382795603,
      "graph_keep": 0.7085714340209961,
      "param_keep": 0.7085714340209961,
      "graph_churn": 0.0028571507427841425,
      "param_churn": 0.0028758887201547623
    },
    {
      "epoch": 117,
      "loss": 1.3121718168258667,
      "task_loss": 1.3121718168258667,
      "train_acc": 0.7215686440467834,
      "val_acc": 0.6901960968971252,
      "test_acc": 0.70686274766922,
      "best_val": 0.6901960968971252,
      "best_test": 0.70686274766922,
      "temperature": 0.5117863042050441,
      "graph_keep": 0.7057141661643982,
      "param_keep": 0.705714225769043,
      "graph_churn": 0.002857126761227846,
      "param_churn": 0.0028770724311470985
    },
    {
      "epoch": 118,
      "loss": 1.3067806959152222,
      "task_loss": 1.3067806959152222,
      "train_acc": 0.7346405386924744,
      "val_acc": 0.7045751810073853,
      "test_acc": 0.7184640765190125,
      "best_val": 0.7045751810073853,
      "best_test": 0.7184640765190125,
      "temperature": 0.5058588262574075,
      "graph_keep": 0.7028570771217346,
      "param_keep": 0.7028571367263794,
      "graph_churn": 0.0028571051079779863,
      "param_churn": 0.0028793932870030403
    },
    {
      "epoch": 119,
      "loss": 1.3109315633773804,
      "task_loss": 1.3109315633773804,
      "train_acc": 0.7320261597633362,
      "val_acc": 0.6993464231491089,
      "test_acc": 0.715032696723938,
      "best_val": 0.7045751810073853,
      "best_test": 0.7184640765190125,
      "temperature": 0.5,
      "graph_keep": 0.6999999284744263,
      "param_keep": 0.7000000476837158,
      "graph_churn": 0.0028571465518325567,
      "param_churn": 0.0028858445584774017
    }
  ],
  "config": {
    "in_dim": 745,
    "hidden_dim": 64,
    "out_dim": 8,
    "num_nodes": 7650,
    "num_edges": 238162,
    "memory_rank": 16,
    "graph_target_keep": 0.7,
    "param_target_keep": 0.7,
    "graph_gamma": 2.0,
    "param_gamma": 2.0,
    "cross_gamma": 0.2,
    "write_beta": 0.25,
    "write_lambda": 0.98,
    "hard_masks": false,
    "seed": 1,
    "use_graph_pruning": true,
    "use_param_pruning": true,
    "use_memory": false,
    "use_cross": false
  }
}